wasar/__init__.py
wasar/agregado.py
wasar/model.py
wasar/parts.py
wasar/plot.py
wasar/wavelet.py
wasar/example/__init__.py
wasar/example/Data/bds/bd_piezo.txt
wasar/example/Data/bds/bd_precipi.txt
wasar/example/Data/shapefiles/Agregados.cpg
wasar/example/Data/shapefiles/Agregados.dbf
wasar/example/Data/shapefiles/Agregados.prj
wasar/example/Data/shapefiles/Agregados.shp
wasar/example/Data/shapefiles/Agregados.shx
wasar/example/Data/shapefiles/Estaciones.cpg
wasar/example/Data/shapefiles/Estaciones.dbf
wasar/example/Data/shapefiles/Estaciones.prj
wasar/example/Data/shapefiles/Estaciones.shp
wasar/example/Data/shapefiles/Estaciones.shx
wasar/example/Data/shapefiles/Piezometros.cpg
wasar/example/Data/shapefiles/Piezometros.dbf
wasar/example/Data/shapefiles/Piezometros.prj
wasar/example/Data/shapefiles/Piezometros.shp
wasar/example/Data/shapefiles/Piezometros.shx
wasar/example/Data/shapefiles/Sentinel_Asc.cpg
wasar/example/Data/shapefiles/Sentinel_Asc.dbf
wasar/example/Data/shapefiles/Sentinel_Asc.prj
wasar/example/Data/shapefiles/Sentinel_Asc.shp
wasar/example/Data/shapefiles/Sentinel_Asc.shx
wasar/example/Data/shapefiles/Sentinel_Desc.cpg
wasar/example/Data/shapefiles/Sentinel_Desc.dbf
wasar/example/Data/shapefiles/Sentinel_Desc.prj
wasar/example/Data/shapefiles/Sentinel_Desc.shp
wasar/example/Data/shapefiles/Sentinel_Desc.shx
wasar/utils/Legend.png
wasar/utils/__init__.py
wasar/utils/_lotes.py
wasar/utils/_utils.py
wasar-0.0.4.dist-info/METADATA
wasar-0.0.4.dist-info/WHEEL
wasar-0.0.4.dist-info/top_level.txt
wasar-0.0.4.dist-info/RECORD
