Metadata-Version: 2.1
Name: wasar
Version: 0.0.4
Summary: Python package for analyzing A-DInSAR time series.
Home-page: https://github.com/MiguelonGonzalez/wasar
Author: Miguel González Jiménez & Carolina Guardiola Albert
Author-email: miguigonn@gmail.com, c.guardiola@igme.es
License: GNU GENERAL PUBLIC LICENSE Version 3
Platform: UNKNOWN
Classifier: Programming Language :: Python
Classifier: Programming Language :: Python :: 3.8
Classifier: License :: OSI Approved :: GNU General Public License v3 (GPLv3)
Classifier: Operating System :: Microsoft :: Windows
Classifier: Natural Language :: Spanish
Classifier: Intended Audience :: Science/Research
Classifier: Topic :: Scientific/Engineering :: GIS
Classifier: Topic :: Scientific/Engineering :: Hydrology
Requires-Dist: geopandas (>=0.10.2)
Requires-Dist: pandas (>=1.3.2)
Requires-Dist: matplotlib (>=3.4.2)
Requires-Dist: folium
